LICENSE
README.md
setup.cfg
setup.py
unit/__init__.py
unit/api/__init__.py
unit/api/account_end_of_day_resource.py
unit/api/account_resource.py
unit/api/api_token_resource.py
unit/api/applicationForm_resource.py
unit/api/application_resource.py
unit/api/atmLocation_resource.py
unit/api/authorization_request_resource.py
unit/api/authorization_resource.py
unit/api/base_resource.py
unit/api/batch_release_resource.py
unit/api/bill_pay_resource.py
unit/api/card_resource.py
unit/api/checkDeposit_resource.py
unit/api/check_payment_resource.py
unit/api/counterparty_resource.py
unit/api/customerToken_resource.py
unit/api/customer_resource.py
unit/api/dispute_resource.py
unit/api/event_resource.py
unit/api/fee_resource.py
unit/api/institution_resource.py
unit/api/payment_resource.py
unit/api/received_payment_resource.py
unit/api/recurring_payment_resource.py
unit/api/repayment_resource.py
unit/api/returnAch_resource.py
unit/api/reward_resource.py
unit/api/statement_resource.py
unit/api/tax_form_resource.py
unit/api/transaction_resource.py
unit/api/webhook_resource.py
unit/models/__init__.py
unit/models/account.py
unit/models/account_end_of_day.py
unit/models/api_token.py
unit/models/application.py
unit/models/applicationForm.py
unit/models/atm_location.py
unit/models/authorization.py
unit/models/authorization_request.py
unit/models/batch_release.py
unit/models/benificial_owner.py
unit/models/bill_pay.py
unit/models/card.py
unit/models/check_deposit.py
unit/models/check_payment.py
unit/models/codecs.py
unit/models/counterparty.py
unit/models/customer.py
unit/models/customerToken.py
unit/models/dispute.py
unit/models/event.py
unit/models/fee.py
unit/models/institution.py
unit/models/payment.py
unit/models/received_payment.py
unit/models/repayment.py
unit/models/returnAch.py
unit/models/reward.py
unit/models/statement.py
unit/models/tax_form.py
unit/models/transaction.py
unit/models/webhook.py
unit/utils/__init__.py
unit/utils/configuration.py
unit/utils/date_utils.py
unit_python_sdk.egg-info/PKG-INFO
unit_python_sdk.egg-info/SOURCES.txt
unit_python_sdk.egg-info/dependency_links.txt
unit_python_sdk.egg-info/requires.txt
unit_python_sdk.egg-info/top_level.txt